twc/__init__.py
twc/_version.py
twc/app.py
twc/commands.py
twc/conditions.py
twc/config.py
twc/consts.py
twc/help.py
twc/layout.py
twc/locale.py
twc/markup.py
twc/settings.py
twc/signals.py
twc/task.py
twc/twutils.py
twc/utils.py
twc/window_stack.py
twc/widgets/__init__.py
twc/widgets/agenda.py
twc/widgets/commandline.py
twc/widgets/completions.py
twc/widgets/formatters.py
twc/widgets/messagebox.py
twc/widgets/statusline.py
twc/widgets/tabs.py
twc/widgets/text.py
twc/widgets/urls.py
twc-0.10.1.data/data/share/man/man1/twc.1
twc-0.10.1.dist-info/LICENSE
twc-0.10.1.dist-info/METADATA
twc-0.10.1.dist-info/WHEEL
twc-0.10.1.dist-info/entry_points.txt
twc-0.10.1.dist-info/top_level.txt
twc-0.10.1.dist-info/RECORD
