Metadata-Version: 2.1
Name: twc
Version: 0.10.1
Summary: TaskWarrior's interactive terminal frontend
Home-page: https://gitlab.com/mgoral/twc
Author: Michał Góral
Author-email: dev@mgoral.org
License: GPLv3+
Platform: linux
Classifier: Development Status :: 4 - Beta
Classifier: Environment :: Console
Classifier: Intended Audience :: End Users/Desktop
Classifier: License :: OSI Approved :: GNU General Public License v3 or later (GPLv3+)
Classifier: Natural Language :: English
Classifier: Operating System :: POSIX
Classifier: Programming Language :: Python :: 3 :: Only
Classifier: Programming Language :: Python :: 3.6
Classifier: Programming Language :: Python :: 3.7
Classifier: Programming Language :: Python :: 3.8
Classifier: Topic :: Utilities
Requires-Python: >=3.6,<3.9
Requires-Dist: prompt-toolkit (==3.0.5)
Requires-Dist: tasklib (==1.1.0)
Requires-Dist: attrs (==19.1.0)
Requires-Dist: mgcomm (>=0.2.0)
